vcfstats/__init__.py
vcfstats/__main__.py
vcfstats/args.toml
vcfstats/cli.py
vcfstats/formula.py
vcfstats/instance.py
vcfstats/macros.py
vcfstats/utils.py
vcfstats-0.7.1.dist-info/METADATA
vcfstats-0.7.1.dist-info/WHEEL
vcfstats-0.7.1.dist-info/entry_points.txt
vcfstats-0.7.1.dist-info/licenses/LICENSE
vcfstats-0.7.1.dist-info/RECORD
