Metadata-Version: 2.4
Name: vcfstats
Version: 0.7.1
Summary: Powerful statistics for VCF files
License: MIT
License-File: LICENSE
Author: pwwang
Author-email: pwwang@pwwang.com
Requires-Python: >=3.9,<4.0
Classifier: License :: OSI Approved :: MIT License
Classifier: Programming Language :: Python :: 3
Classifier: Programming Language :: Python :: 3.9
Classifier: Programming Language :: Python :: 3.10
Classifier: Programming Language :: Python :: 3.11
Classifier: Programming Language :: Python :: 3.12
Classifier: Programming Language :: Python :: 3.13
Classifier: Programming Language :: Python :: 3.14
Requires-Dist: argx (>=0.3,<0.4)
Requires-Dist: cyvcf2 (>=0.30,<0.31)
Requires-Dist: datar[pandas] (<0.15.9)
Requires-Dist: lark (>=1.2,<2.0)
Requires-Dist: plotnine-prism (>=0.3.2,<0.4.0)
Requires-Dist: py (>=1.11,<2.0)
Requires-Dist: python-slugify (>=8,<9)
Requires-Dist: rich (>=13,<14)
Project-URL: Homepage, https://github.com/pwwang/vcfstats
Project-URL: Repository, https://github.com/pwwang/vcfstats
